motify-1.0.0.dist-info/licenses/LICENSE
src/__init__.py
src/app.py
src/services/__init__.py
src/services/downloader.py
src/services/spotify_service.py
src/ui/__init__.py
src/ui/history_tab.py
src/ui/lyrics_tab.py
src/ui/main_window.py
src/ui/queue_tab.py
src/ui/search_tab.py
src/ui/settings_tab.py
src/ui/stats_tab.py
src/ui/youtube_tab.py
src/utils/__init__.py
src/utils/config.py
src/utils/ui_styles.py
motify-1.0.0.dist-info/METADATA
motify-1.0.0.dist-info/WHEEL
motify-1.0.0.dist-info/entry_points.txt
motify-1.0.0.dist-info/top_level.txt
motify-1.0.0.dist-info/RECORD
