Metadata-Version: 2.4
Name: motify
Version: 1.0.0
Summary: Motify is a python script that takes a playlist or a track or an album link directly from spotify and download the songs related to that link with the best quality alongs side embedding the songs data to enjoy the experiment with it's full potential
Home-page: https://github.com/mosh3eb/motify
Author: Mosh3eb
Author-email: Mosh3eb <Mosh2eb@gmail.com>
License: MIT License
Project-URL: Homepage, https://github.com/mosh3eb/motify
Project-URL: Documentation, https://mosh3eb.github.io/motify/
Project-URL: Repository, https://github.com/mosh3eb/motify.git
Project-URL: Bug Tracker, https://github.com/mosh3eb/motify/issues
Keywords: music,downloader,spotify,youtube,audio,player
Classifier: Development Status :: 5 - Production/Stable
Classifier: Intended Audience :: End Users/Desktop
Classifier: License :: OSI Approved :: MIT License
Classifier: Operating System :: OS Independent
Classifier: Programming Language :: Python :: 3
Classifier: Programming Language :: Python :: 3.10
Classifier: Programming Language :: Python :: 3.11
Classifier: Topic :: Multimedia :: Sound/Audio
Classifier: Topic :: Multimedia :: Sound/Audio :: Players
Requires-Python: >=3.10
License-File: LICENSE
Requires-Dist: requests>=2.28.0
Requires-Dist: ttkbootstrap>=1.10.0
Requires-Dist: yt-dlp>=2023.3.4
Requires-Dist: mutagen>=1.46.0
Requires-Dist: plyer>=2.1.0
Requires-Dist: spotipy>=2.23.0
Requires-Dist: watchdog>=2.3.1
Requires-Dist: pillow>=9.5.0
Requires-Dist: matplotlib>=3.5.0
Requires-Dist: beautifulsoup4>=4.12.0
Requires-Dist: lxml>=4.9.0
Dynamic: author
Dynamic: home-page
Dynamic: license-file
Dynamic: requires-python
